arch/__init__.py
arch/admin.py
arch/apps.py
arch/models.py
arch/serializers.py
arch/views.py
arch/__pycache__/__init__.cpython-313.opt-1.pyc
arch/__pycache__/admin.cpython-313.opt-1.pyc
arch/__pycache__/apps.cpython-313.opt-1.pyc
arch/__pycache__/models.cpython-313.opt-1.pyc
arch/__pycache__/serializers.cpython-313.opt-1.pyc
arch/__pycache__/views.cpython-313.opt-1.pyc
arch/migrations/0001_initial.py
arch/migrations/__init__.py
arch/migrations/__pycache__/0001_initial.cpython-313.opt-1.pyc
arch/migrations/__pycache__/__init__.cpython-313.opt-1.pyc
domains/__init__.py
domains/admin.py
domains/apps.py
domains/models.py
domains/serializers.py
domains/views.py
domains/__pycache__/__init__.cpython-313.opt-1.pyc
domains/__pycache__/admin.cpython-313.opt-1.pyc
domains/__pycache__/apps.cpython-313.opt-1.pyc
domains/__pycache__/models.cpython-313.opt-1.pyc
domains/__pycache__/serializers.cpython-313.opt-1.pyc
domains/__pycache__/views.cpython-313.opt-1.pyc
domains/migrations/0001_initial.py
domains/migrations/__init__.py
domains/migrations/__pycache__/0001_initial.cpython-313.opt-1.pyc
domains/migrations/__pycache__/__init__.cpython-313.opt-1.pyc
etc/patchman/apache.conf.example
etc/patchman/local_settings.py
hosts/__init__.py
hosts/admin.py
hosts/apps.py
hosts/forms.py
hosts/managers.py
hosts/models.py
hosts/serializers.py
hosts/urls.py
hosts/utils.py
hosts/views.py
hosts/__pycache__/__init__.cpython-313.opt-1.pyc
hosts/__pycache__/admin.cpython-313.opt-1.pyc
hosts/__pycache__/apps.cpython-313.opt-1.pyc
hosts/__pycache__/forms.cpython-313.opt-1.pyc
hosts/__pycache__/managers.cpython-313.opt-1.pyc
hosts/__pycache__/models.cpython-313.opt-1.pyc
hosts/__pycache__/serializers.cpython-313.opt-1.pyc
hosts/__pycache__/urls.cpython-313.opt-1.pyc
hosts/__pycache__/utils.cpython-313.opt-1.pyc
hosts/__pycache__/views.cpython-313.opt-1.pyc
hosts/migrations/0001_initial.py
hosts/migrations/0002_initial.py
hosts/migrations/0003_host_modules.py
hosts/migrations/__init__.py
patchman-3.0.19.dist-info/AUTHORS
patchman-3.0.19.dist-info/COPYING
patchman-3.0.19.dist-info/METADATA
patchman-3.0.19.dist-info/WHEEL
patchman-3.0.19.dist-info/top_level.txt
patchman-3.0.19.dist-info/RECORD
