Metadata-Version: 2.2
Name: patchman
Version: 3.0.19
Summary: Django based patch status monitoring tool for linux systems
Home-page: http://patchman.openbytes.ie/
Author: Marcus Furlong
Author-email: furlongm@gmail.com
License: GPLv3
Keywords: django patch status monitoring linux spacewalk patchman
Classifier: Development Status :: 5 - Production/Stable
Classifier: Environment :: Web Environment
Classifier: Framework :: Django
Classifier: Topic :: Internet :: WWW/HTTP :: WSGI :: Application
Classifier: License :: OSI Approved :: GNU General Public License v3 (GPLv3)
License-File: COPYING
License-File: AUTHORS
Requires-Dist: Django==3.2.25
Requires-Dist: django-tagging==0.5.0
Requires-Dist: django-extensions==3.2.1
Requires-Dist: django-bootstrap3==23.1
Requires-Dist: progressbar==2.5
Requires-Dist: python-debian==0.1.49
Requires-Dist: lxml==5.2.2
Requires-Dist: defusedxml==0.7.1
Requires-Dist: PyYAML==6.0.1
Requires-Dist: chardet==4.0.0
Requires-Dist: requests==2.32.3
Requires-Dist: colorama==0.4.4
Requires-Dist: djangorestframework==3.13.1
Requires-Dist: django-filter==21.1
Requires-Dist: humanize==3.13.1
Requires-Dist: version-utils==0.3.0
Requires-Dist: python-magic==0.4.25
Requires-Dist: pymemcache==4.0.0
Dynamic: author
Dynamic: author-email
Dynamic: classifier
Dynamic: description
Dynamic: description-content-type
Dynamic: home-page
Dynamic: keywords
Dynamic: license
Dynamic: requires-dist
Dynamic: summary
